Workbook
Name Slicer_Category: #N/A
Name Slicer_Product: #N/A
Name Slicer_Region: #N/A
Name Slicer_SalesPerson: #N/A

Sheet Excel_Data_Analytics_Dataset
A1: OrderID | B1: OrderDate | C1: Region | D1: Category | E1: Product | F1: CustomerName | G1: SalesPerson | H1: Sales | I1: Cost
A2: 1 | B2: 45660 | C2: West | D2: Furniture | E2: Table | F2: Customer_16 | G2: Sneha | H2: 5811 | I2: 5067
A3: 2 | B3: 45710 | C3: North | D3: Furniture | E3: Desk | F3: Customer_19 | G3: Sneha | H3: 13553 | I3: 8173
A4: 3 | B4: 45714 | C4: South | D4: Electronics | E4: Mobile | F4: Customer_45 | G4: Sneha | H4: 7987 | I4: 5653
A5: 4 | B5: 45710 | C5: West | D5: Furniture | E5: Chair | F5: Customer_30 | G5: Farhan | H5: 3254 | I5: 2435
A6: 5 | B6: 45702 | C6: South | D6: Electronics | E6: Mobile | F6: Customer_40 | G6: Farhan | H6: 13732 | I6: 11076
A7: 6 | B7: 45669 | C7: South | D7: Furniture | E7: Table | F7: Customer_34 | G7: Sneha | H7: 17328 | I7: 14130
A8: 7 | B8: 45687 | C8: North | D8: Electronics | E8: Laptop | F8: Customer_14 | G8: Aisha | H8: 16650 | I8: 14634
A9: 8 | B9: 45661 | C9: South | D9: Electronics | E9: Headphones | F9: Customer_1 | G9: Sneha | H9: 4964 | I9: 3181
A10: 9 | B10: 45705 | C10: North | D10: Furniture | E10: Table | F10: Customer_49 | G10: Farhan | H10: 19497 | I10: 16208
A11: 10 | B11: 45693 | C11: South | D11: Electronics | E11: Tablet | F11: Customer_34 | G11: Rahul | H11: 29094 | I11: 19174
A12: 11 | B12: 45666 | C12: West | D12: Electronics | E12: Mobile | F12: Customer_39 | G12: Nikhil | H12: 27904 | I12: 24463
A13: 12 | B13: 45680 | C13: North | D13: Electronics | E13: Headphones | F13: Customer_23 | G13: Aisha | H13: 9233 | I13: 6766
... A201: 200 | B201: 45683 | C201: East | D201: Electronics | E201: Headphones | F201: Customer_22 | G201: Nikhil | H201: 6437 | I201: 4292

Sheet  Employee_Salary
A1: Name | B1: Salary | C1: Total_Sales | D1: Rank
A2: Aisha | B2: 45000 | C2: =SUMIF(Assg!G2:G201,' Employee_Salary'!A2,Assg!H2:H201) -> 750452 | D2: =RANK(C2,$C$2:$C$6) -> 1
A3: Rahul | B3: 42000 | C3: =SUMIF(Assg!G3:G202,' Employee_Salary'!A3,Assg!H3:H202) -> 633574 | D3: =RANK(C3,$C$2:$C$6) -> 4
A4: Nikhil | B4: 40000 | C4: =SUMIF(Assg!G4:G203,' Employee_Salary'!A4,Assg!H4:H203) -> 648534 | D4: =RANK(C4,$C$2:$C$6) -> 3
A5: Sneha | B5: 47000 | C5: =SUMIF(Assg!G5:G204,' Employee_Salary'!A5,Assg!H5:H204) -> 481886 | D5: =RANK(C5,$C$2:$C$6) -> 5
A6: Farhan | B6: 43000 | C6: =SUMIF(Assg!G6:G205,' Employee_Salary'!A6,Assg!H6:H205) -> 690149 | D6: =RANK(C6,$C$2:$C$6) -> 2

Sheet Assg -1
A1: OrderID | B1: OrderDate | C1: Region | D1: Category | E1: Product | F1: CustomerName | G1: SalesPerson | H1: Sales | I1: Cost
A2: 1 | B2: 45660 | C2: West | D2: Furniture | E2: Table | F2: Customer_16 | G2: Sneha | H2: 5811 | I2: 5067 | L2: Excel Data Analytics – Practical Assignment 1
A3: 2 | B3: 45710 | C3: North | D3: Furniture | E3: Desk | F3: Customer_19 | G3: Sneha | H3: 13553 | I3: 8173 | L3: Section A – Data Cleaning | P3: Answers
A4: 3 | B4: 45714 | C4: South | D4: Electronics | E4: Mobile | F4: Customer_45 | G4: Sneha | H4: 7987 | I4: 5653 | L4: 1. Format OrderDate as Date format. | P4: Home->Numbers->Custom-dd-mm-yy
A5: 4 | B5: 45710 | C5: West | D5: Furniture | E5: Chair | F5: Customer_30 | G5: Farhan | H5: 3254 | I5: 2435 | L5: 2. Remove duplicate records (if any). | P5: No Duplicates found
A6: 5 | B6: 45702 | C6: South | D6: Electronics | E6: Mobile | F6: Customer_40 | G6: Farhan | H6: 13732 | I6: 11076 | L6: 3. Remove extra spaces in text fields. | P6: No Extra Space
A7: 6 | B7: 45669 | C7: South | D7: Furniture | E7: Table | F7: Customer_34 | G7: Sneha | H7: 17328 | I7: 14130 | L7: 4. Convert the dataset into an Excel Table (Ctrl + T). | P7: Ctrl + t
A8: 7 | B8: 45687 | C8: North | D8: Electronics | E8: Laptop | F8: Customer_14 | G8: Aisha | H8: 16650 | I8: 14634
A9: 8 | B9: 45661 | C9: South | D9: Electronics | E9: Headphones | F9: Customer_1 | G9: Sneha | H9: 4964 | I9: 3181
A10: 9 | B10: 45705 | C10: North | D10: Furniture | E10: Table | F10: Customer_49 | G10: Farhan | H10: 19497 | I10: 16208
A11: 10 | B11: 45693 | C11: South | D11: Electronics | E11: Tablet | F11: Customer_34 | G11: Rahul | H11: 29094 | I11: 19174
A12: 11 | B12: 45666 | C12: West | D12: Electronics | E12: Mobile | F12: Customer_39 | G12: Nikhil | H12: 27904 | I12: 24463
A13: 12 | B13: 45680 | C13: North | D13: Electronics | E13: Headphones | F13: Customer_23 | G13: Aisha | H13: 9233 | I13: 6766
A14: 13 | B14: 45713 | C14: East | D14: Furniture | E14: Desk | F14: Customer_38 | G14: Sneha | H14: 27329 | I14: 18038
A15: 14 | B15: 45700 | C15: West | D15: Furniture | E15: Desk | F15: Customer_5 | G15: Rahul | H15: 6994 | I15: 5062
A16: 15 | B16: 45684 | C16: East | D16: Furniture | E16: Table | F16: Customer_4 | G16: Sneha | H16: 6822 | I16: 5407
A17: 16 | B17: 45670 | C17: East | D17: Electronics | E17: Headphones | F17: Customer_39 | G17: Farhan | H17: 14681 | I17: 11778
A18: 17 | B18: 45671 | C18: West | D18: Electronics | E18: Laptop | F18: Customer_10 | G18: Aisha | H18: 21800 | I18: 16672
A19: 18 | B19: 45706 | C19: East | D19: Electronics | E19: Headphones | F19: Customer_23 | G19: Nikhil | H19: 27543 | I19: 21241
... A201: 200 | B201: 45683 | C201: East | D201: Electronics | E201: Headphones | F201: Customer_22 | G201: Nikhil | H201: 6437 | I201: 4292

Sheet Assg-2
A1: OrderID | B1: OrderDate | C1: Region | D1: Category | E1: Product | F1: CustomerName | G1: SalesPerson | H1: Sales | I1: Cost | J1: Profit | K1: Profit %
A2: 1 | B2: 45660 | C2: West | D2: Furniture | E2: Table | F2: Customer_16 | G2: Sneha | H2: 5811 | I2: 5067 | J2: =H2-I2 -> 744 | K2: =J2/H2 -> 0.12803304 | M2: Section B – Basic Calculations | N2: Answers
A3: 2 | B3: 45710 | C3: North | D3: Furniture | E3: Desk | F3: Customer_19 | G3: Sneha | H3: 13553 | I3: 8173 | J3: =H3-I3 -> 5380 | K3: =J3/H3 -> 0.39696008 | M3: 5. Add Profit = Sales – Cost column. | N3: Formula(Sales-Cost) (=H2-I2)
A4: 3 | B4: 45714 | C4: South | D4: Electronics | E4: Mobile | F4: Customer_45 | G4: Sneha | H4: 7987 | I4: 5653 | J4: =H4-I4 -> 2334 | K4: =J4/H4 -> 0.29222487 | M4: 6. Add Profit % column. | N4: Formula (Profit/Sales) (=J2/H2) and Number -> % )
A5: 4 | B5: 45710 | C5: West | D5: Furniture | E5: Chair | F5: Customer_30 | G5: Farhan | H5: 3254 | I5: 2435 | J5: =H5-I5 -> 819 | K5: =J5/H5 -> 0.25169023 | M5: 7. Calculate:
A6: 5 | B6: 45702 | C6: South | D6: Electronics | E6: Mobile | F6: Customer_40 | G6: Farhan | H6: 13732 | I6: 11076 | J6: =H6-I6 -> 2656 | K6: =J6/H6 -> 0.19341684 | M6: • Total Sales | N6: Formula(Sum of Sales) (=subtotal(9,H2:H201) | O6: =SUBTOTAL(9,H2:H201) -> 3235200
A7: 6 | B7: 45669 | C7: South | D7: Furniture | E7: Table | F7: Customer_34 | G7: Sneha | H7: 17328 | I7: 14130 | J7: =H7-I7 -> 3198 | K7: =J7/H7 -> 0.18455679 | M7: • Total Cost | N7: Formula(Sum of Cost) (=subtotal(9,I2:I201) | O7: =SUBTOTAL(9,I2:I201) -> 2447134
A8: 7 | B8: 45687 | C8: North | D8: Electronics | E8: Laptop | F8: Customer_14 | G8: Aisha | H8: 16650 | I8: 14634 | J8: =H8-I8 -> 2016 | K8: =J8/H8 -> 0.12108108 | M8: • Total Profit | N8: Formula(Sum of Profit) (=subtotal(9,J2:J201) | O8: =SUBTOTAL(9,J2:J201) -> 788066
A9: 8 | B9: 45661 | C9: South | D9: Electronics | E9: Headphones | F9: Customer_1 | G9: Sneha | H9: 4964 | I9: 3181 | J9: =H9-I9 -> 1783 | K9: =J9/H9 -> 0.35918614 | M9: • Total Orders | N9: Formula(count of orders) (=count(A2:A201) | O9: =COUNT(A2:A201) -> 200
A10: 9 | B10: 45705 | C10: North | D10: Furniture | E10: Table | F10: Customer_49 | G10: Farhan | H10: 19497 | I10: 16208 | J10: =H10-I10 -> 3289 | K10: =J10/H10 -> 0.16869262 | M10: 8. Calculate Average Sales per order. | N10: Formula(avg Sales) (=count(H2:H201) | O10: =AVERAGE(H2:H201) -> 16176
A11: 10 | B11: 45693 | C11: South | D11: Electronics | E11: Tablet | F11: Customer_34 | G11: Rahul | H11: 29094 | I11: 19174 | J11: =H11-I11 -> 9920 | K11: =J11/H11 -> 0.34096377
A12: 11 | B12: 45666 | C12: West | D12: Electronics | E12: Mobile | F12: Customer_39 | G12: Nikhil | H12: 27904 | I12: 24463 | J12: =H12-I12 -> 3441 | K12: =J12/H12 -> 0.12331565
A13: 12 | B13: 45680 | C13: North | D13: Electronics | E13: Headphones | F13: Customer_23 | G13: Aisha | H13: 9233 | I13: 6766 | J13: =H13-I13 -> 2467 | K13: =J13/H13 -> 0.26719376
A14: 13 | B14: 45713 | C14: East | D14: Furniture | E14: Desk | F14: Customer_38 | G14: Sneha | H14: 27329 | I14: 18038 | J14: =H14-I14 -> 9291 | K14: =J14/H14 -> 0.33996853
A15: 14 | B15: 45700 | C15: West | D15: Furniture | E15: Desk | F15: Customer_5 | G15: Rahul | H15: 6994 | I15: 5062 | J15: =H15-I15 -> 1932 | K15: =J15/H15 -> 0.27623677
A16: 15 | B16: 45684 | C16: East | D16: Furniture | E16: Table | F16: Customer_4 | G16: Sneha | H16: 6822 | I16: 5407 | J16: =H16-I16 -> 1415 | K16: =J16/H16 -> 0.20741718
A17: 16 | B17: 45670 | C17: East | D17: Electronics | E17: Headphones | F17: Customer_39 | G17: Farhan | H17: 14681 | I17: 11778 | J17: =H17-I17 -> 2903 | K17: =J17/H17 -> 0.19773857
A18: 17 | B18: 45671 | C18: West | D18: Electronics | E18: Laptop | F18: Customer_10 | G18: Aisha | H18: 21800 | I18: 16672 | J18: =H18-I18 -> 5128 | K18: =J18/H18 -> 0.23522936
A19: 18 | B19: 45706 | C19: East | D19: Electronics | E19: Headphones | F19: Customer_23 | G19: Nikhil | H19: 27543 | I19: 21241 | J19: =H19-I19 -> 6302 | K19: =J19/H19 -> 0.22880587
A20: 19 | B20: 45709 | C20: South | D20: Furniture | E20: Cupboard | F20: Customer_45 | G20: Aisha | H20: 8177 | I20: 6277 | J20: =H20-I20 -> 1900 | K20: =J20/H20 -> 0.23235906
A21: 20 | B21: 45688 | C21: North | D21: Electronics | E21: Tablet | F21: Customer_22 | G21: Rahul | H21: 17261 | I21: 14516 | J21: =H21-I21 -> 2745 | K21: =J21/H21 -> 0.15902902
A22: 21 | B22: 45680 | C22: East | D22: Electronics | E22: Laptop | F22: Customer_25 | G22: Aisha | H22: 13080 | I22: 11394 | J22: =H22-I22 -> 1686 | K22: =J22/H22 -> 0.12889908
... A201: 200 | B201: 45683 | C201: East | D201: Electronics | E201: Headphones | F201: Customer_22 | G201: Nikhil | H201: 6437 | I201: 4292 | J201: =H201-I201 -> 2145 | K201: =J201/H201 -> 0.33322977
C203: Total | H203: =SUBTOTAL(9,H2:H201) -> 3235200 | I203: =SUBTOTAL(9,I2:I201) -> 2447134 | J203: =SUBTOTAL(9,J2:J201) -> 788066

Sheet Assg
A1: OrderID | B1: OrderDate | C1: Region | D1: Category | E1: Product | F1: CustomerName | G1: SalesPerson | H1: Sales | I1: Cost | J1: Profit | K1: Profit % | L1: Profit_performance | M1: Salary | N1: Sales_ratio | O1: Comission | P1: Rank | Q1: Running_total
A2: 1 | B2: 45660 | C2: West | D2: Furniture | E2: Table | F2: Customer_16 | G2: Sneha | H2: 5811 | I2: 5067 | J2: =H2-I2 -> 744 | K2: =J2/H2 -> 0.12803304 | L2: {=_xlfn.IFS(J2>15000,"Excellent",J2>=5000,"Good",J2<5000,"Poor")} -> Poor | M2: =_xlfn.XLOOKUP(G2,' Employee_Salary'!$A$2:$A$6,' Employee_Salary'!$B$2:$B$6) -> 47000 | N2: =M2/H2 -> 8.0881088 | O2: =IF(D2="Electronics",H2*5%,IF(D2="Furniture",H2*8%,0)) -> 464.88 | P2: =_xlfn.RANK.EQ(H2,$H$2:$H$201,0) -> 179 | Q2: =SUMIFS($H$2:$H$201,$B$2:$B$201,"<="&B2) -> 118866 | R2: Section C – Functions Practice | S2: Formula | T2: Result
A3: 2 | B3: 45710 | C3: North | D3: Furniture | E3: Desk | F3: Customer_19 | G3: Sneha | H3: 13553 | I3: 8173 | J3: =H3-I3 -> 5380 | K3: =J3/H3 -> 0.39696008 | L3: {=_xlfn.IFS(J3>15000,"Excellent",J3>=5000,"Good",J3<5000,"Poor")} -> Good | M3: =_xlfn.XLOOKUP(G3,' Employee_Salary'!$A$1:A7,' Employee_Salary'!$B$1:B7,FALSE) -> 47000 | N3: =M3/H3 -> 3.4678669 | O3: =IF(D3="Electronics",H3*5%,IF(D3="Furniture",H3*8%,0)) -> 1084.24 | P3: =_xlfn.RANK.EQ(H3,$H$2:$H$201,0) -> 120 | Q3: =SUMIFS($H$2:$H$201,$B$2:$B$201,"<="&B3) -> 2944836 | R3: 9. Count orders from North region. | S3: Formula(=Countif(C2:C201,"North")) | T3: =COUNTIF(C2:C201,"North") -> 42
A4: 3 | B4: 45714 | C4: South | D4: Electronics | E4: Mobile | F4: Customer_45 | G4: Sneha | H4: 7987 | I4: 5653 | J4: =H4-I4 -> 2334 | K4: =J4/H4 -> 0.29222487 | L4: {=_xlfn.IFS(J4>15000,"Excellent",J4>=5000,"Good",J4<5000,"Poor")} -> Poor | M4: {=_xlfn.XLOOKUP(G4,' Employee_Salary'!$A$1:A8,' Employee_Salary'!$B$1:B8,FALSE)} -> 47000 | N4: =M4/H4 -> 5.8845624 | O4: =IF(D4="Electronics",H4*5%,IF(D4="Furniture",H4*8%,0)) -> 399.35 | P4: =_xlfn.RANK.EQ(H4,$H$2:$H$201,0) -> 163 | Q4: =SUMIFS($H$2:$H$201,$B$2:$B$201,"<="&B4) -> 3096876 | R4: 10.Count Electronics category orders. | S4: Formula(=Countif(D2:D201,"Electronics")) | T4: =COUNTIF(D2:D201,"Electronics") -> 96
A5: 4 | B5: 45710 | C5: West | D5: Furniture | E5: Chair | F5: Customer_30 | G5: Farhan | H5: 3254 | I5: 2435 | J5: =H5-I5 -> 819 | K5: =J5/H5 -> 0.25169023 | L5: {=_xlfn.IFS(J5>15000,"Excellent",J5>=5000,"Good",J5<5000,"Poor")} -> Poor | M5: {=_xlfn.XLOOKUP(G5,' Employee_Salary'!$A$1:A9,' Employee_Salary'!$B$1:B9,FALSE)} -> 43000 | N5: =M5/H5 -> 13.214505 | O5: =IF(D5="Electronics",H5*5%,IF(D5="Furniture",H5*8%,0)) -> 260.32 | P5: =_xlfn.RANK.EQ(H5,$H$2:$H$201,0) -> 198 | Q5: =SUMIFS($H$2:$H$201,$B$2:$B$201,"<="&B5) -> 2944836 | R5: 11.Find Maximum, Minimum, and Average sales.
A6: 5 | B6: 45702 | C6: South | D6: Electronics | E6: Mobile | F6: Customer_40 | G6: Farhan | H6: 13732 | I6: 11076 | J6: =H6-I6 -> 2656 | K6: =J6/H6 -> 0.19341684 | L6: {=_xlfn.IFS(J6>15000,"Excellent",J6>=5000,"Good",J6<5000,"Poor")} -> Poor | M6: {=_xlfn.XLOOKUP(G6,' Employee_Salary'!$A$1:A10,' Employee_Salary'!$B$1:B10,FALSE)} -> 43000 | N6: =M6/H6 -> 3.131372 | O6: =IF(D6="Electronics",H6*5%,IF(D6="Furniture",H6*8%,0)) -> 686.6 | P6: =_xlfn.RANK.EQ(H6,$H$2:$H$201,0) -> 117 | Q6: =SUMIFS($H$2:$H$201,$B$2:$B$201,"<="&B6) -> 2448350 | R6: Max | S6: Max(H2:H201) | T6: =MAX(H2:H201) -> 29811
A7: 6 | B7: 45669 | C7: South | D7: Furniture | E7: Table | F7: Customer_34 | G7: Sneha | H7: 17328 | I7: 14130 | J7: =H7-I7 -> 3198 | K7: =J7/H7 -> 0.18455679 | L7: {=_xlfn.IFS(J7>15000,"Excellent",J7>=5000,"Good",J7<5000,"Poor")} -> Poor | M7: {=_xlfn.XLOOKUP(G7,' Employee_Salary'!$A$1:A11,' Employee_Salary'!$B$1:B11,FALSE)} -> 47000 | N7: =M7/H7 -> 2.712373 | O7: =IF(D7="Electronics",H7*5%,IF(D7="Furniture",H7*8%,0)) -> 1386.24 | P7: =_xlfn.RANK.EQ(H7,$H$2:$H$201,0) -> 90 | Q7: =SUMIFS($H$2:$H$201,$B$2:$B$201,"<="&B7) -> 665652 | R7: Min | S7: Min(H2:H201) | T7: =MIN(H2:H201) -> 3003
A8: 7 | B8: 45687 | C8: North | D8: Electronics | E8: Laptop | F8: Customer_14 | G8: Aisha | H8: 16650 | I8: 14634 | J8: =H8-I8 -> 2016 | K8: =J8/H8 -> 0.12108108 | L8: {=_xlfn.IFS(J8>15000,"Excellent",J8>=5000,"Good",J8<5000,"Poor")} -> Poor | M8: {=_xlfn.XLOOKUP(G8,' Employee_Salary'!$A$1:A12,' Employee_Salary'!$B$1:B12,FALSE)} -> 45000 | N8: =M8/H8 -> 2.7027027 | O8: =IF(D8="Electronics",H8*5%,IF(D8="Furniture",H8*8%,0)) -> 832.5 | P8: =_xlfn.RANK.EQ(H8,$H$2:$H$201,0) -> 101 | Q8: =SUMIFS($H$2:$H$201,$B$2:$B$201,"<="&B8) -> 1735136 | R8: Avg | S8: avg(H2:H201) | T8: =AVERAGE(H2:H201) -> 16176
A9: 8 | B9: 45661 | C9: South | D9: Electronics | E9: Headphones | F9: Customer_1 | G9: Sneha | H9: 4964 | I9: 3181 | J9: =H9-I9 -> 1783 | K9: =J9/H9 -> 0.35918614 | L9: {=_xlfn.IFS(J9>15000,"Excellent",J9>=5000,"Good",J9<5000,"Poor")} -> Poor | M9: {=_xlfn.XLOOKUP(G9,' Employee_Salary'!$A$1:A13,' Employee_Salary'!$B$1:B13,FALSE)} -> 47000 | N9: =M9/H9 -> 9.4681708 | O9: =IF(D9="Electronics",H9*5%,IF(D9="Furniture",H9*8%,0)) -> 248.2 | P9: =_xlfn.RANK.EQ(H9,$H$2:$H$201,0) -> 186 | Q9: =SUMIFS($H$2:$H$201,$B$2:$B$201,"<="&B9) -> 165400 | R9: 12.Use IF/IFS:
A10: 9 | B10: 45705 | C10: North | D10: Furniture | E10: Table | F10: Customer_49 | G10: Farhan | H10: 19497 | I10: 16208 | J10: =H10-I10 -> 3289 | K10: =J10/H10 -> 0.16869262 | L10: {=_xlfn.IFS(J10>15000,"Excellent",J10>=5000,"Good",J10<5000,"Poor")} -> Poor | M10: {=_xlfn.XLOOKUP(G10,' Employee_Salary'!$A$1:A14,' Employee_Salary'!$B$1:B14,FALSE)} -> 43000 | N10: =M10/H10 -> 2.2054675 | O10: =IF(D10="Electronics",H10*5%,IF(D10="Furniture",H10*8%,0)) -> 1559.76 | P10: =_xlfn.RANK.EQ(H10,$H$2:$H$201,0) -> 70 | Q10: =SUMIFS($H$2:$H$201,$B$2:$B$201,"<="&B10) -> 2691046 | R10: • Profit > 15000 ? Excellent | S10: Ifs(J2 > 15000, "Excellent" , J2 > =5000 , "Good", J2 < 5000,"Poor") | T10: =IF(J2>15000,"Excellent", IF(J2>=5000,"Good","Poor")) -> Poor
A11: 10 | B11: 45693 | C11: South | D11: Electronics | E11: Tablet | F11: Customer_34 | G11: Rahul | H11: 29094 | I11: 19174 | J11: =H11-I11 -> 9920 | K11: =J11/H11 -> 0.34096377 | L11: {=_xlfn.IFS(J11>15000,"Excellent",J11>=5000,"Good",J11<5000,"Poor")} -> Good | M11: {=_xlfn.XLOOKUP(G11,' Employee_Salary'!$A$1:A15,' Employee_Salary'!$B$1:B15,FALSE)} -> 42000 | N11: =M11/H11 -> 1.4435966 | O11: =IF(D11="Electronics",H11*5%,IF(D11="Furniture",H11*8%,0)) -> 1454.7 | P11: =_xlfn.RANK.EQ(H11,$H$2:$H$201,0) -> 3 | Q11: =SUMIFS($H$2:$H$201,$B$2:$B$201,"<="&B11) -> 1945841 | R11: • 5000–15000 ? Good
A12: 11 | B12: 45666 | C12: West | D12: Electronics | E12: Mobile | F12: Customer_39 | G12: Nikhil | H12: 27904 | I12: 24463 | J12: =H12-I12 -> 3441 | K12: =J12/H12 -> 0.12331565 | L12: {=_xlfn.IFS(J12>15000,"Excellent",J12>=5000,"Good",J12<5000,"Poor")} -> Poor | M12: {=_xlfn.XLOOKUP(G12,' Employee_Salary'!$A$1:A16,' Employee_Salary'!$B$1:B16,FALSE)} -> 40000 | N12: =M12/H12 -> 1.4334862 | O12: =IF(D12="Electronics",H12*5%,IF(D12="Furniture",H12*8%,0)) -> 1395.2 | P12: =_xlfn.RANK.EQ(H12,$H$2:$H$201,0) -> 14 | Q12: =SUMIFS($H$2:$H$201,$B$2:$B$201,"<="&B12) -> 480218 | R12: • Else ? Poor
A13: 12 | B13: 45680 | C13: North | D13: Electronics | E13: Headphones | F13: Customer_23 | G13: Aisha | H13: 9233 | I13: 6766 | J13: =H13-I13 -> 2467 | K13: =J13/H13 -> 0.26719376 | L13: {=_xlfn.IFS(J13>15000,"Excellent",J13>=5000,"Good",J13<5000,"Poor")} -> Poor | M13: {=_xlfn.XLOOKUP(G13,' Employee_Salary'!$A$1:A17,' Employee_Salary'!$B$1:B17,FALSE)} -> 45000 | N13: =M13/H13 -> 4.8738222 | O13: =IF(D13="Electronics",H13*5%,IF(D13="Furniture",H13*8%,0)) -> 461.65 | P13: =_xlfn.RANK.EQ(H13,$H$2:$H$201,0) -> 155 | Q13: =SUMIFS($H$2:$H$201,$B$2:$B$201,"<="&B13) -> 1349916
A14: 13 | B14: 45713 | C14: East | D14: Furniture | E14: Desk | F14: Customer_38 | G14: Sneha | H14: 27329 | I14: 18038 | J14: =H14-I14 -> 9291 | K14: =J14/H14 -> 0.33996853 | L14: {=_xlfn.IFS(J14>15000,"Excellent",J14>=5000,"Good",J14<5000,"Poor")} -> Good | M14: {=_xlfn.XLOOKUP(G14,' Employee_Salary'!$A$1:A18,' Employee_Salary'!$B$1:B18,FALSE)} -> 47000 | N14: =M14/H14 -> 1.7197848 | O14: =IF(D14="Electronics",H14*5%,IF(D14="Furniture",H14*8%,0)) -> 2186.32 | P14: =_xlfn.RANK.EQ(H14,$H$2:$H$201,0) -> 19 | Q14: =SUMIFS($H$2:$H$201,$B$2:$B$201,"<="&B14) -> 3053221
A15: 14 | B15: 45700 | C15: West | D15: Furniture | E15: Desk | F15: Customer_5 | G15: Rahul | H15: 6994 | I15: 5062 | J15: =H15-I15 -> 1932 | K15: =J15/H15 -> 0.27623677 | L15: {=_xlfn.IFS(J15>15000,"Excellent",J15>=5000,"Good",J15<5000,"Poor")} -> Poor | M15: {=_xlfn.XLOOKUP(G15,' Employee_Salary'!$A$1:A19,' Employee_Salary'!$B$1:B19,FALSE)} -> 42000 | N15: =M15/H15 -> 6.0051473 | O15: =IF(D15="Electronics",H15*5%,IF(D15="Furniture",H15*8%,0)) -> 559.52 | P15: =_xlfn.RANK.EQ(H15,$H$2:$H$201,0) -> 171 | Q15: =SUMIFS($H$2:$H$201,$B$2:$B$201,"<="&B15) -> 2334388 | R15: Section D – Lookup & Logical
A16: 15 | B16: 45684 | C16: East | D16: Furniture | E16: Table | F16: Customer_4 | G16: Sneha | H16: 6822 | I16: 5407 | J16: =H16-I16 -> 1415 | K16: =J16/H16 -> 0.20741718 | L16: {=_xlfn.IFS(J16>15000,"Excellent",J16>=5000,"Good",J16<5000,"Poor")} -> Poor | M16: {=_xlfn.XLOOKUP(G16,' Employee_Salary'!$A$1:A20,' Employee_Salary'!$B$1:B20,FALSE)} -> 47000 | N16: =M16/H16 -> 6.8894752 | O16: =IF(D16="Electronics",H16*5%,IF(D16="Furniture",H16*8%,0)) -> 545.76 | P16: =_xlfn.RANK.EQ(H16,$H$2:$H$201,0) -> 172 | Q16: =SUMIFS($H$2:$H$201,$B$2:$B$201,"<="&B16) -> 1596018 | R16: 13.Fetch Salary from Employee_Salary sheet using VLOOKUP/XLOOKUP. | S16: VLOOKUP(G2, ' Employee_Salary'!$A$2:$B$6, 2, FALSE) XLOOKUP(SalesPerson, Employee_Salary!$A$2:$A$6, Employee_Salary!$B$2:$B$6) | T16: =VLOOKUP(G2, ' Employee_Salary'!A1:$B$6,2,FALSE) -> 47000
A17: 16 | B17: 45670 | C17: East | D17: Electronics | E17: Headphones | F17: Customer_39 | G17: Farhan | H17: 14681 | I17: 11778 | J17: =H17-I17 -> 2903 | K17: =J17/H17 -> 0.19773857 | L17: {=_xlfn.IFS(J17>15000,"Excellent",J17>=5000,"Good",J17<5000,"Poor")} -> Poor | M17: {=_xlfn.XLOOKUP(G17,' Employee_Salary'!$A$1:A21,' Employee_Salary'!$B$1:B21,FALSE)} -> 43000 | N17: =M17/H17 -> 2.9289558 | O17: =IF(D17="Electronics",H17*5%,IF(D17="Furniture",H17*8%,0)) -> 734.05 | P17: =_xlfn.RANK.EQ(H17,$H$2:$H$201,0) -> 111 | Q17: =SUMIFS($H$2:$H$201,$B$2:$B$201,"<="&B17) -> 757644 | R17: 14.Calculate Salary-to-Sales ratio. | S17: Salary/Sales ( M2/H2) | T17: =M2/H2 -> 8.0881088
A18: 17 | B18: 45671 | C18: West | D18: Electronics | E18: Laptop | F18: Customer_10 | G18: Aisha | H18: 21800 | I18: 16672 | J18: =H18-I18 -> 5128 | K18: =J18/H18 -> 0.23522936 | L18: {=_xlfn.IFS(J18>15000,"Excellent",J18>=5000,"Good",J18<5000,"Poor")} -> Good | M18: {=_xlfn.XLOOKUP(G18,' Employee_Salary'!$A$1:A22,' Employee_Salary'!$B$1:B22,FALSE)} -> 45000 | N18: =M18/H18 -> 2.0642202 | O18: =IF(D18="Electronics",H18*5%,IF(D18="Furniture",H18*8%,0)) -> 1090 | P18: =_xlfn.RANK.EQ(H18,$H$2:$H$201,0) -> 55 | Q18: =SUMIFS($H$2:$H$201,$B$2:$B$201,"<="&B18) -> 841403 | R18: 15.Calculate Commission:
A19: 18 | B19: 45706 | C19: East | D19: Electronics | E19: Headphones | F19: Customer_23 | G19: Nikhil | H19: 27543 | I19: 21241 | J19: =H19-I19 -> 6302 | K19: =J19/H19 -> 0.22880587 | L19: {=_xlfn.IFS(J19>15000,"Excellent",J19>=5000,"Good",J19<5000,"Poor")} -> Good | M19: {=_xlfn.XLOOKUP(G19,' Employee_Salary'!$A$1:A23,' Employee_Salary'!$B$1:B23,FALSE)} -> 40000 | N19: =M19/H19 -> 1.4522746 | O19: =IF(D19="Electronics",H19*5%,IF(D19="Furniture",H19*8%,0)) -> 1377.15 | P19: =_xlfn.RANK.EQ(H19,$H$2:$H$201,0) -> 17 | Q19: =SUMIFS($H$2:$H$201,$B$2:$B$201,"<="&B19) -> 2761759 | R19: • Electronics ? 5%
A20: 19 | B20: 45709 | C20: South | D20: Furniture | E20: Cupboard | F20: Customer_45 | G20: Aisha | H20: 8177 | I20: 6277 | J20: =H20-I20 -> 1900 | K20: =J20/H20 -> 0.23235906 | L20: {=_xlfn.IFS(J20>15000,"Excellent",J20>=5000,"Good",J20<5000,"Poor")} -> Poor | M20: {=_xlfn.XLOOKUP(G20,' Employee_Salary'!$A$1:A24,' Employee_Salary'!$B$1:B24,FALSE)} -> 45000 | N20: =M20/H20 -> 5.5032408 | O20: =IF(D20="Electronics",H20*5%,IF(D20="Furniture",H20*8%,0)) -> 654.16 | P20: =_xlfn.RANK.EQ(H20,$H$2:$H$201,0) -> 162 | Q20: =SUMIFS($H$2:$H$201,$B$2:$B$201,"<="&B20) -> 2860992 | R20: • Furniture ? 8% | S20: IF(D2="Electronics", H2*5%, IF(D2="Furniture", H2*8%, 0)) | T20: =IF(D2="Electronics", H2*5%, IF(D2="Furniture", H2*8%, 0)) -> 464.88
A21: 20 | B21: 45688 | C21: North | D21: Electronics | E21: Tablet | F21: Customer_22 | G21: Rahul | H21: 17261 | I21: 14516 | J21: =H21-I21 -> 2745 | K21: =J21/H21 -> 0.15902902 | L21: {=_xlfn.IFS(J21>15000,"Excellent",J21>=5000,"Good",J21<5000,"Poor")} -> Poor | M21: {=_xlfn.XLOOKUP(G21,' Employee_Salary'!$A$1:A25,' Employee_Salary'!$B$1:B25,FALSE)} -> 42000 | N21: =M21/H21 -> 2.433231 | O21: =IF(D21="Electronics",H21*5%,IF(D21="Furniture",H21*8%,0)) -> 863.05 | P21: =_xlfn.RANK.EQ(H21,$H$2:$H$201,0) -> 92 | Q21: =SUMIFS($H$2:$H$201,$B$2:$B$201,"<="&B21) -> 1789203 | R21: 16.Rank SalesPerson based on total sales (highest = 1). | S21: RANK.EQ(H2,$H$2:$H$201,0) | T21: =_xlfn.RANK.EQ(H2,$H$2:$H$201,0) -> 179
A22: 21 | B22: 45680 | C22: East | D22: Electronics | E22: Laptop | F22: Customer_25 | G22: Aisha | H22: 13080 | I22: 11394 | J22: =H22-I22 -> 1686 | K22: =J22/H22 -> 0.12889908 | L22: {=_xlfn.IFS(J22>15000,"Excellent",J22>=5000,"Good",J22<5000,"Poor")} -> Poor | M22: {=_xlfn.XLOOKUP(G22,' Employee_Salary'!$A$1:A26,' Employee_Salary'!$B$1:B26,FALSE)} -> 45000 | N22: =M22/H22 -> 3.440367 | O22: =IF(D22="Electronics",H22*5%,IF(D22="Furniture",H22*8%,0)) -> 654 | P22: =_xlfn.RANK.EQ(H22,$H$2:$H$201,0) -> 123 | Q22: =SUMIFS($H$2:$H$201,$B$2:$B$201,"<="&B22) -> 1349916 | S22: Done Total Sales and Rank in Employee _ Salary Sheet
A23: 22 | B23: 45683 | C23: West | D23: Furniture | E23: Desk | F23: Customer_31 | G23: Rahul | H23: 12676 | I23: 8182 | J23: =H23-I23 -> 4494 | K23: =J23/H23 -> 0.35452824 | L23: {=_xlfn.IFS(J23>15000,"Excellent",J23>=5000,"Good",J23<5000,"Poor")} -> Poor | M23: {=_xlfn.XLOOKUP(G23,' Employee_Salary'!$A$1:A27,' Employee_Salary'!$B$1:B27,FALSE)} -> 42000 | N23: =M23/H23 -> 3.3133481 | O23: =IF(D23="Electronics",H23*5%,IF(D23="Furniture",H23*8%,0)) -> 1014.08 | P23: =_xlfn.RANK.EQ(H23,$H$2:$H$201,0) -> 130 | Q23: =SUMIFS($H$2:$H$201,$B$2:$B$201,"<="&B23) -> 1589196
A24: 23 | B24: 45679 | C24: West | D24: Furniture | E24: Chair | F24: Customer_31 | G24: Sneha | H24: 12995 | I24: 10838 | J24: =H24-I24 -> 2157 | K24: =J24/H24 -> 0.16598692 | L24: {=_xlfn.IFS(J24>15000,"Excellent",J24>=5000,"Good",J24<5000,"Poor")} -> Poor | M24: {=_xlfn.XLOOKUP(G24,' Employee_Salary'!$A$1:A28,' Employee_Salary'!$B$1:B28,FALSE)} -> 47000 | N24: =M24/H24 -> 3.6167757 | O24: =IF(D24="Electronics",H24*5%,IF(D24="Furniture",H24*8%,0)) -> 1039.6 | P24: =_xlfn.RANK.EQ(H24,$H$2:$H$201,0) -> 124 | Q24: =SUMIFS($H$2:$H$201,$B$2:$B$201,"<="&B24) -> 1247618
A25: 24 | B25: 45714 | C25: South | D25: Furniture | E25: Desk | F25: Customer_3 | G25: Rahul | H25: 26402 | I25: 22809 | J25: =H25-I25 -> 3593 | K25: =J25/H25 -> 0.13608818 | L25: {=_xlfn.IFS(J25>15000,"Excellent",J25>=5000,"Good",J25<5000,"Poor")} -> Poor | M25: {=_xlfn.XLOOKUP(G25,' Employee_Salary'!$A$1:A29,' Employee_Salary'!$B$1:B29,FALSE)} -> 42000 | N25: =M25/H25 -> 1.5907886 | O25: =IF(D25="Electronics",H25*5%,IF(D25="Furniture",H25*8%,0)) -> 2112.16 | P25: =_xlfn.RANK.EQ(H25,$H$2:$H$201,0) -> 27 | Q25: =SUMIFS($H$2:$H$201,$B$2:$B$201,"<="&B25) -> 3096876 | R25: Section E – Advanced Formulas
A26: 25 | B26: 45677 | C26: South | D26: Electronics | E26: Headphones | F26: Customer_8 | G26: Rahul | H26: 20499 | I26: 13107 | J26: =H26-I26 -> 7392 | K26: =J26/H26 -> 0.36060296 | L26: {=_xlfn.IFS(J26>15000,"Excellent",J26>=5000,"Good",J26<5000,"Poor")} -> Good | M26: {=_xlfn.XLOOKUP(G26,' Employee_Salary'!$A$1:A30,' Employee_Salary'!$B$1:B30,FALSE)} -> 42000 | N26: =M26/H26 -> 2.0488804 | O26: =IF(D26="Electronics",H26*5%,IF(D26="Furniture",H26*8%,0)) -> 1024.95 | P26: =_xlfn.RANK.EQ(H26,$H$2:$H$201,0) -> 63 | Q26: =SUMIFS($H$2:$H$201,$B$2:$B$201,"<="&B26) -> 1137341 | R26: 17. Create Running Total (Cumulative Sales) by date. | S26: SUMIFS($H$2:$H$201,$B$2:$B$201,"<="&B2) | T26: =SUMIFS($H$2:$H$201,$B$2:$B$201,"<="&B2) -> 118866
A27: 26 | B27: 45682 | C27: East | D27: Furniture | E27: Table | F27: Customer_18 | G27: Nikhil | H27: 22507 | I27: 15607 | J27: =H27-I27 -> 6900 | K27: =J27/H27 -> 0.30657129 | L27: {=_xlfn.IFS(J27>15000,"Excellent",J27>=5000,"Good",J27<5000,"Poor")} -> Good | M27: {=_xlfn.XLOOKUP(G27,' Employee_Salary'!$A$1:A31,' Employee_Salary'!$B$1:B31,FALSE)} -> 40000 | N27: =M27/H27 -> 1.7772249 | O27: =IF(D27="Electronics",H27*5%,IF(D27="Furniture",H27*8%,0)) -> 1800.56 | P27: =_xlfn.RANK.EQ(H27,$H$2:$H$201,0) -> 50 | Q27: =SUMIFS($H$2:$H$201,$B$2:$B$201,"<="&B27) -> 1502635 | R27: 18. Find Unique Customer count. | S27: COUNTA(UNIQUE(F2:F201)) | T27: =COUNTA(_xlfn.UNIQUE(F2:F201)) -> 50
A28: 27 | B28: 45702 | C28: East | D28: Furniture | E28: Chair | F28: Customer_3 | G28: Nikhil | H28: 4786 | I28: 3412 | J28: =H28-I28 -> 1374 | K28: =J28/H28 -> 0.28708734 | L28: {=_xlfn.IFS(J28>15000,"Excellent",J28>=5000,"Good",J28<5000,"Poor")} -> Poor | M28: {=_xlfn.XLOOKUP(G28,' Employee_Salary'!$A$1:A32,' Employee_Salary'!$B$1:B32,FALSE)} -> 40000 | N28: =M28/H28 -> 8.35771 | O28: =IF(D28="Electronics",H28*5%,IF(D28="Furniture",H28*8%,0)) -> 382.88 | P28: =_xlfn.RANK.EQ(H28,$H$2:$H$201,0) -> 189 | Q28: =SUMIFS($H$2:$H$201,$B$2:$B$201,"<="&B28) -> 2448350 | R28: 19. Identify Top 3 sales orders. | S28: XLOOKUP(LARGE(H2:H201,1),H2:H201,A2:A201) (Order ID) result | T28: =_xlfn.XLOOKUP(LARGE(H2:H201,1),H2:H201,A2:A201) -> 144
A29: 28 | B29: 45668 | C29: West | D29: Electronics | E29: Laptop | F29: Customer_22 | G29: Aisha | H29: 26850 | I29: 20892 | J29: =H29-I29 -> 5958 | K29: =J29/H29 -> 0.22189944 | L29: {=_xlfn.IFS(J29>15000,"Excellent",J29>=5000,"Good",J29<5000,"Poor")} -> Good | M29: {=_xlfn.XLOOKUP(G29,' Employee_Salary'!$A$1:A33,' Employee_Salary'!$B$1:B33,FALSE)} -> 45000 | N29: =M29/H29 -> 1.6759777 | O29: =IF(D29="Electronics",H29*5%,IF(D29="Furniture",H29*8%,0)) -> 1342.5 | P29: =_xlfn.RANK.EQ(H29,$H$2:$H$201,0) -> 22 | Q29: =SUMIFS($H$2:$H$201,$B$2:$B$201,"<="&B29) -> 550830 | S29: XLOOKUP(LARGE(H3:H201,2),H3:H201,A3:A201) | T29: =_xlfn.XLOOKUP(LARGE(H3:H202,2),H3:H202,A3:A202) -> 64
A30: 29 | B30: 45687 | C30: East | D30: Electronics | E30: Mobile | F30: Customer_12 | G30: Farhan | H30: 19466 | I30: 17460 | J30: =H30-I30 -> 2006 | K30: =J30/H30 -> 0.10305147 | L30: {=_xlfn.IFS(J30>15000,"Excellent",J30>=5000,"Good",J30<5000,"Poor")} -> Poor | M30: {=_xlfn.XLOOKUP(G30,' Employee_Salary'!$A$1:A34,' Employee_Salary'!$B$1:B34,FALSE)} -> 43000 | N30: =M30/H30 -> 2.2089798 | O30: =IF(D30="Electronics",H30*5%,IF(D30="Furniture",H30*8%,0)) -> 973.3 | P30: =_xlfn.RANK.EQ(H30,$H$2:$H$201,0) -> 72 | Q30: =SUMIFS($H$2:$H$201,$B$2:$B$201,"<="&B30) -> 1735136 | S30: XLOOKUP(LARGE(H4:H201,3),H4:H201,A4:A201) | T30: =_xlfn.XLOOKUP(LARGE(H4:H203,3),H4:H203,A4:A203) -> 10
A31: 30 | B31: 45703 | C31: West | D31: Furniture | E31: Desk | F31: Customer_23 | G31: Nikhil | H31: 14784 | I31: 9723 | J31: =H31-I31 -> 5061 | K31: =J31/H31 -> 0.34232955 | L31: {=_xlfn.IFS(J31>15000,"Excellent",J31>=5000,"Good",J31<5000,"Poor")} -> Good | M31: {=_xlfn.XLOOKUP(G31,' Employee_Salary'!$A$1:A35,' Employee_Salary'!$B$1:B35,FALSE)} -> 40000 | N31: =M31/H31 -> 2.7056277 | O31: =IF(D31="Electronics",H31*5%,IF(D31="Furniture",H31*8%,0)) -> 1182.72 | P31: =_xlfn.RANK.EQ(H31,$H$2:$H$201,0) -> 110 | Q31: =SUMIFS($H$2:$H$201,$B$2:$B$201,"<="&B31) -> 2463134 | R31: 20. Identify Bottom 2 sales orders. | S31: XLOOKUP(SMALL(H2:H201,1),H2:H201,A2:A201) (Order ID) result | T31: =_xlfn.XLOOKUP(SMALL(H2:H201,1),H2:H201,A2:A201) -> 150
A32: 31 | B32: 45670 | C32: West | D32: Electronics | E32: Headphones | F32: Customer_13 | G32: Nikhil | H32: 28085 | I32: 22509 | J32: =H32-I32 -> 5576 | K32: =J32/H32 -> 0.19854015 | L32: {=_xlfn.IFS(J32>15000,"Excellent",J32>=5000,"Good",J32<5000,"Poor")} -> Good | M32: {=_xlfn.XLOOKUP(G32,' Employee_Salary'!$A$1:A36,' Employee_Salary'!$B$1:B36,FALSE)} -> 40000 | N32: =M32/H32 -> 1.4242478 | O32: =IF(D32="Electronics",H32*5%,IF(D32="Furniture",H32*8%,0)) -> 1404.25 | P32: =_xlfn.RANK.EQ(H32,$H$2:$H$201,0) -> 12 | Q32: =SUMIFS($H$2:$H$201,$B$2:$B$201,"<="&B32) -> 757644 | S32: XLOOKUP(SMALL(H3:H201,1),H3:H201,A3:A201) (Order ID) result | T32: =_xlfn.XLOOKUP(SMALL(H3:H202,2),H3:H202,A3:A202) -> 93
A33: 32 | B33: 45675 | C33: East | D33: Electronics | E33: Laptop | F33: Customer_15 | G33: Rahul | H33: 11264 | I33: 9957 | J33: =H33-I33 -> 1307 | K33: =J33/H33 -> 0.11603338 | L33: {=_xlfn.IFS(J33>15000,"Excellent",J33>=5000,"Good",J33<5000,"Poor")} -> Poor | M33: {=_xlfn.XLOOKUP(G33,' Employee_Salary'!$A$1:A37,' Employee_Salary'!$B$1:B37,FALSE)} -> 42000 | N33: =M33/H33 -> 3.7286932 | O33: =IF(D33="Electronics",H33*5%,IF(D33="Furniture",H33*8%,0)) -> 563.2 | P33: =_xlfn.RANK.EQ(H33,$H$2:$H$201,0) -> 145 | Q33: =SUMIFS($H$2:$H$201,$B$2:$B$201,"<="&B33) -> 980127
A34: 33 | B34: 45680 | C34: South | D34: Electronics | E34: Headphones | F34: Customer_25 | G34: Aisha | H34: 10384 | I34: 7534 | J34: =H34-I34 -> 2850 | K34: =J34/H34 -> 0.27446071 | L34: {=_xlfn.IFS(J34>15000,"Excellent",J34>=5000,"Good",J34<5000,"Poor")} -> Poor | M34: {=_xlfn.XLOOKUP(G34,' Employee_Salary'!$A$1:A38,' Employee_Salary'!$B$1:B38,FALSE)} -> 45000 | N34: =M34/H34 -> 4.3335901 | O34: =IF(D34="Electronics",H34*5%,IF(D34="Furniture",H34*8%,0)) -> 519.2 | P34: =_xlfn.RANK.EQ(H34,$H$2:$H$201,0) -> 149 | Q34: =SUMIFS($H$2:$H$201,$B$2:$B$201,"<="&B34) -> 1349916 | R34: 21. Use SUMIFS to calculate:
A35: 34 | B35: 45674 | C35: North | D35: Electronics | E35: Mobile | F35: Customer_5 | G35: Rahul | H35: 13816 | I35: 9688 | J35: =H35-I35 -> 4128 | K35: =J35/H35 -> 0.29878402 | L35: {=_xlfn.IFS(J35>15000,"Excellent",J35>=5000,"Good",J35<5000,"Poor")} -> Poor | M35: {=_xlfn.XLOOKUP(G35,' Employee_Salary'!$A$1:A39,' Employee_Salary'!$B$1:B39,FALSE)} -> 42000 | N35: =M35/H35 -> 3.0399537 | O35: =IF(D35="Electronics",H35*5%,IF(D35="Furniture",H35*8%,0)) -> 690.8 | P35: =_xlfn.RANK.EQ(H35,$H$2:$H$201,0) -> 115 | Q35: =SUMIFS($H$2:$H$201,$B$2:$B$201,"<="&B35) -> 947177 | R35: • Electronics sales in North region | S35: SUMIFS(H2:H201,D2:D201,"Electronics",C2:C201,"North") | T35: =SUMIFS(H2:H201,D2:D201,"Electronics",C2:C201,"North") -> 344005
A36: 35 | B36: 45673 | C36: West | D36: Furniture | E36: Desk | F36: Customer_32 | G36: Sneha | H36: 19945 | I36: 17781 | J36: =H36-I36 -> 2164 | K36: =J36/H36 -> 0.10849837 | L36: {=_xlfn.IFS(J36>15000,"Excellent",J36>=5000,"Good",J36<5000,"Poor")} -> Poor | M36: {=_xlfn.XLOOKUP(G36,' Employee_Salary'!$A$1:A40,' Employee_Salary'!$B$1:B40,FALSE)} -> 47000 | N36: =M36/H36 -> 2.3564803 | O36: =IF(D36="Electronics",H36*5%,IF(D36="Furniture",H36*8%,0)) -> 1595.6 | P36: =_xlfn.RANK.EQ(H36,$H$2:$H$201,0) -> 66 | Q36: =SUMIFS($H$2:$H$201,$B$2:$B$201,"<="&B36) -> 933361 | R36: • Furniture sales in South region | S36: SUMIFS(H2:H201,D2:D201,"Furniture",C2:C201,"South") | T36: =SUMIFS(H2:H201,D2:D201,"Furniture",C2:C201,"South") -> 522975
A37: 36 | B37: 45713 | C37: West | D37: Furniture | E37: Desk | F37: Customer_4 | G37: Aisha | H37: 12316 | I37: 10577 | J37: =H37-I37 -> 1739 | K37: =J37/H37 -> 0.14119844 | L37: {=_xlfn.IFS(J37>15000,"Excellent",J37>=5000,"Good",J37<5000,"Poor")} -> Poor | M37: {=_xlfn.XLOOKUP(G37,' Employee_Salary'!$A$1:A41,' Employee_Salary'!$B$1:B41,FALSE)} -> 45000 | N37: =M37/H37 -> 3.6537837 | O37: =IF(D37="Electronics",H37*5%,IF(D37="Furniture",H37*8%,0)) -> 985.28 | P37: =_xlfn.RANK.EQ(H37,$H$2:$H$201,0) -> 135 | Q37: =SUMIFS($H$2:$H$201,$B$2:$B$201,"<="&B37) -> 3053221 | R37: • Sales for a selected SalesPerson | S37: SUMIFS(H2:H201,G2:G201,G36) | T37: =SUMIFS(H2:H201,G2:G201,G36) -> 509237
A38: 37 | B38: 45658 | C38: West | D38: Electronics | E38: Laptop | F38: Customer_28 | G38: Rahul | H38: 5269 | I38: 3833 | J38: =H38-I38 -> 1436 | K38: =J38/H38 -> 0.27253748 | L38: {=_xlfn.IFS(J38>15000,"Excellent",J38>=5000,"Good",J38<5000,"Poor")} -> Poor | M38: {=_xlfn.XLOOKUP(G38,' Employee_Salary'!$A$1:A42,' Employee_Salary'!$B$1:B42,FALSE)} -> 42000 | N38: =M38/H38 -> 7.971152 | O38: =IF(D38="Electronics",H38*5%,IF(D38="Furniture",H38*8%,0)) -> 263.45 | P38: =_xlfn.RANK.EQ(H38,$H$2:$H$201,0) -> 182 | Q38: =SUMIFS($H$2:$H$201,$B$2:$B$201,"<="&B38) -> 49160
A39: 38 | B39: 45661 | C39: North | D39: Furniture | E39: Desk | F39: Customer_22 | G39: Rahul | H39: 23738 | I39: 16560 | J39: =H39-I39 -> 7178 | K39: =J39/H39 -> 0.30238436 | L39: {=_xlfn.IFS(J39>15000,"Excellent",J39>=5000,"Good",J39<5000,"Poor")} -> Good | M39: {=_xlfn.XLOOKUP(G39,' Employee_Salary'!$A$1:A43,' Employee_Salary'!$B$1:B43,FALSE)} -> 42000 | N39: =M39/H39 -> 1.769315 | O39: =IF(D39="Electronics",H39*5%,IF(D39="Furniture",H39*8%,0)) -> 1899.04 | P39: =_xlfn.RANK.EQ(H39,$H$2:$H$201,0) -> 40 | Q39: =SUMIFS($H$2:$H$201,$B$2:$B$201,"<="&B39) -> 165400
A40: 39 | B40: 45717 | C40: East | D40: Furniture | E40: Table | F40: Customer_14 | G40: Farhan | H40: 23819 | I40: 17508 | J40: =H40-I40 -> 6311 | K40: =J40/H40 -> 0.26495655 | L40: {=_xlfn.IFS(J40>15000,"Excellent",J40>=5000,"Good",J40<5000,"Poor")} -> Good | M40: {=_xlfn.XLOOKUP(G40,' Employee_Salary'!$A$1:A44,' Employee_Salary'!$B$1:B44,FALSE)} -> 43000 | N40: =M40/H40 -> 1.8052815 | O40: =IF(D40="Electronics",H40*5%,IF(D40="Furniture",H40*8%,0)) -> 1905.52 | P40: =_xlfn.RANK.EQ(H40,$H$2:$H$201,0) -> 39 | Q40: =SUMIFS($H$2:$H$201,$B$2:$B$201,"<="&B40) -> 3235200 | R40: Section F – Analysis Tasks
A41: 40 | B41: 45696 | C41: North | D41: Electronics | E41: Laptop | F41: Customer_38 | G41: Farhan | H41: 4280 | I41: 2925 | J41: =H41-I41 -> 1355 | K41: =J41/H41 -> 0.31658879 | L41: {=_xlfn.IFS(J41>15000,"Excellent",J41>=5000,"Good",J41<5000,"Poor")} -> Poor | M41: {=_xlfn.XLOOKUP(G41,' Employee_Salary'!$A$1:A45,' Employee_Salary'!$B$1:B45,FALSE)} -> 43000 | N41: =M41/H41 -> 10.046729 | O41: =IF(D41="Electronics",H41*5%,IF(D41="Furniture",H41*8%,0)) -> 214 | P41: =_xlfn.RANK.EQ(H41,$H$2:$H$201,0) -> 192 | Q41: =SUMIFS($H$2:$H$201,$B$2:$B$201,"<="&B41) -> 2074177 | R41: 22. Highlight orders with negative profit using Conditional Formatting. | S41: J2<0 | T41: =J2<0 -> FALSE
A42: 41 | B42: 45691 | C42: South | D42: Electronics | E42: Laptop | F42: Customer_37 | G42: Rahul | H42: 18083 | I42: 13861 | J42: =H42-I42 -> 4222 | K42: =J42/H42 -> 0.23347896 | L42: {=_xlfn.IFS(J42>15000,"Excellent",J42>=5000,"Good",J42<5000,"Poor")} -> Poor | M42: {=_xlfn.XLOOKUP(G42,' Employee_Salary'!$A$1:A46,' Employee_Salary'!$B$1:B46,FALSE)} -> 42000 | N42: =M42/H42 -> 2.3226235 | O42: =IF(D42="Electronics",H42*5%,IF(D42="Furniture",H42*8%,0)) -> 904.15 | P42: =_xlfn.RANK.EQ(H42,$H$2:$H$201,0) -> 80 | Q42: =SUMIFS($H$2:$H$201,$B$2:$B$201,"<="&B42) -> 1908942 | R42: 23. Find:
A43: 42 | B43: 45681 | C43: North | D43: Furniture | E43: Desk | F43: Customer_3 | G43: Sneha | H43: 22615 | I43: 14629 | J43: =H43-I43 -> 7986 | K43: =J43/H43 -> 0.35312845 | L43: {=_xlfn.IFS(J43>15000,"Excellent",J43>=5000,"Good",J43<5000,"Poor")} -> Good | M43: {=_xlfn.XLOOKUP(G43,' Employee_Salary'!$A$1:A47,' Employee_Salary'!$B$1:B47,FALSE)} -> 47000 | N43: =M43/H43 -> 2.0782666 | O43: =IF(D43="Electronics",H43*5%,IF(D43="Furniture",H43*8%,0)) -> 1809.2 | P43: =_xlfn.RANK.EQ(H43,$H$2:$H$201,0) -> 48 | Q43: =SUMIFS($H$2:$H$201,$B$2:$B$201,"<="&B43) -> 1463299 | R43: • Best performing SalesPerson | S43: XLOOKUP(MAX(' Employee_Salary'!C1:C6),' Employee_Salary'!C1:C6,' Employee_Salary'!A1:A6) | T43: =_xlfn.XLOOKUP(MAX(' Employee_Salary'!C1:C6),' Employee_Salary'!C1:C6,' Employee_Salary'!A1:A6) -> Aisha
A44: 43 | B44: 45668 | C44: South | D44: Electronics | E44: Tablet | F44: Customer_16 | G44: Rahul | H44: 16811 | I44: 13746 | J44: =H44-I44 -> 3065 | K44: =J44/H44 -> 0.1823211 | L44: {=_xlfn.IFS(J44>15000,"Excellent",J44>=5000,"Good",J44<5000,"Poor")} -> Poor | M44: {=_xlfn.XLOOKUP(G44,' Employee_Salary'!$A$1:A48,' Employee_Salary'!$B$1:B48,FALSE)} -> 42000 | N44: =M44/H44 -> 2.4983642 | O44: =IF(D44="Electronics",H44*5%,IF(D44="Furniture",H44*8%,0)) -> 840.55 | P44: =_xlfn.RANK.EQ(H44,$H$2:$H$201,0) -> 97 | Q44: =SUMIFS($H$2:$H$201,$B$2:$B$201,"<="&B44) -> 550830 | R44: • Top Product by revenue | S44: XLOOKUP(MAX(Product!B1:B9),Product!B1:B9,Product!A1#) | T44: {=_xlfn.XLOOKUP(MAX(Product!B1:B9),Product!B1:B9,_xlfn.ANCHORARRAY(Product!A1))} -> Desk
A45: 44 | B45: 45682 | C45: East | D45: Furniture | E45: Chair | F45: Customer_28 | G45: Sneha | H45: 12859 | I45: 8499 | J45: =H45-I45 -> 4360 | K45: =J45/H45 -> 0.33906214 | L45: {=_xlfn.IFS(J45>15000,"Excellent",J45>=5000,"Good",J45<5000,"Poor")} -> Poor | M45: {=_xlfn.XLOOKUP(G45,' Employee_Salary'!$A$1:A49,' Employee_Salary'!$B$1:B49,FALSE)} -> 47000 | N45: =M45/H45 -> 3.6550276 | O45: =IF(D45="Electronics",H45*5%,IF(D45="Furniture",H45*8%,0)) -> 1028.72 | P45: =_xlfn.RANK.EQ(H45,$H$2:$H$201,0) -> 125 | Q45: =SUMIFS($H$2:$H$201,$B$2:$B$201,"<="&B45) -> 1502635 | R45: • Lowest sales day | S45: XLOOKUP(MIN(H2:H201),H2:H201,B2:B201) | T45: =_xlfn.XLOOKUP(MIN(H2:H201),H2:H201,B2:B201) -> 45699
A46: 45 | B46: 45694 | C46: East | D46: Electronics | E46: Headphones | F46: Customer_10 | G46: Rahul | H46: 9025 | I46: 5975 | J46: =H46-I46 -> 3050 | K46: =J46/H46 -> 0.33795014 | L46: {=_xlfn.IFS(J46>15000,"Excellent",J46>=5000,"Good",J46<5000,"Poor")} -> Poor | M46: {=_xlfn.XLOOKUP(G46,' Employee_Salary'!$A$1:A50,' Employee_Salary'!$B$1:B50,FALSE)} -> 42000 | N46: =M46/H46 -> 4.6537396 | O46: =IF(D46="Electronics",H46*5%,IF(D46="Furniture",H46*8%,0)) -> 451.25 | P46: =_xlfn.RANK.EQ(H46,$H$2:$H$201,0) -> 157 | Q46: =SUMIFS($H$2:$H$201,$B$2:$B$201,"<="&B46) -> 1993799
A47: 46 | B47: 45704 | C47: North | D47: Furniture | E47: Cupboard | F47: Customer_32 | G47: Nikhil | H47: 27125 | I47: 24151 | J47: =H47-I47 -> 2974 | K47: =J47/H47 -> 0.10964055 | L47: {=_xlfn.IFS(J47>15000,"Excellent",J47>=5000,"Good",J47<5000,"Poor")} -> Poor | M47: {=_xlfn.XLOOKUP(G47,' Employee_Salary'!$A$1:A51,' Employee_Salary'!$B$1:B51,FALSE)} -> 40000 | N47: =M47/H47 -> 1.4746544 | O47: =IF(D47="Electronics",H47*5%,IF(D47="Furniture",H47*8%,0)) -> 2170 | P47: =_xlfn.RANK.EQ(H47,$H$2:$H$201,0) -> 21 | Q47: =SUMIFS($H$2:$H$201,$B$2:$B$201,"<="&B47) -> 2568758
A48: 47 | B48: 45663 | C48: East | D48: Electronics | E48: Tablet | F48: Customer_28 | G48: Aisha | H48: 4910 | I48: 3805 | J48: =H48-I48 -> 1105 | K48: =J48/H48 -> 0.22505092 | L48: {=_xlfn.IFS(J48>15000,"Excellent",J48>=5000,"Good",J48<5000,"Poor")} -> Poor | M48: {=_xlfn.XLOOKUP(G48,' Employee_Salary'!$A$1:A52,' Employee_Salary'!$B$1:B52,FALSE)} -> 45000 | N48: =M48/H48 -> 9.1649695 | O48: =IF(D48="Electronics",H48*5%,IF(D48="Furniture",H48*8%,0)) -> 245.5 | P48: =_xlfn.RANK.EQ(H48,$H$2:$H$201,0) -> 187 | Q48: =SUMIFS($H$2:$H$201,$B$2:$B$201,"<="&B48) -> 314278
A49: 48 | B49: 45687 | C49: South | D49: Furniture | E49: Cupboard | F49: Customer_13 | G49: Rahul | H49: 13768 | I49: 10313 | J49: =H49-I49 -> 3455 | K49: =J49/H49 -> 0.25094422 | L49: {=_xlfn.IFS(J49>15000,"Excellent",J49>=5000,"Good",J49<5000,"Poor")} -> Poor | M49: {=_xlfn.XLOOKUP(G49,' Employee_Salary'!$A$1:A53,' Employee_Salary'!$B$1:B53,FALSE)} -> 42000 | N49: =M49/H49 -> 3.050552 | O49: =IF(D49="Electronics",H49*5%,IF(D49="Furniture",H49*8%,0)) -> 1101.44 | P49: =_xlfn.RANK.EQ(H49,$H$2:$H$201,0) -> 116 | Q49: =SUMIFS($H$2:$H$201,$B$2:$B$201,"<="&B49) -> 1735136
A50: 49 | B50: 45681 | C50: South | D50: Furniture | E50: Desk | F50: Customer_25 | G50: Nikhil | H50: 28518 | I50: 25660 | J50: =H50-I50 -> 2858 | K50: =J50/H50 -> 0.10021741 | L50: {=_xlfn.IFS(J50>15000,"Excellent",J50>=5000,"Good",J50<5000,"Poor")} -> Poor | M50: {=_xlfn.XLOOKUP(G50,' Employee_Salary'!$A$1:A54,' Employee_Salary'!$B$1:B54,FALSE)} -> 40000 | N50: =M50/H50 -> 1.4026229 | O50: =IF(D50="Electronics",H50*5%,IF(D50="Furniture",H50*8%,0)) -> 2281.44 | P50: =_xlfn.RANK.EQ(H50,$H$2:$H$201,0) -> 8 | Q50: =SUMIFS($H$2:$H$201,$B$2:$B$201,"<="&B50) -> 1463299
A51: 50 | B51: 45706 | C51: East | D51: Furniture | E51: Table | F51: Customer_37 | G51: Aisha | H51: 24630 | I51: 16859 | J51: =H51-I51 -> 7771 | K51: =J51/H51 -> 0.31550954 | L51: {=_xlfn.IFS(J51>15000,"Excellent",J51>=5000,"Good",J51<5000,"Poor")} -> Good | M51: {=_xlfn.XLOOKUP(G51,' Employee_Salary'!$A$1:A55,' Employee_Salary'!$B$1:B55,FALSE)} -> 45000 | N51: =M51/H51 -> 1.8270402 | O51: =IF(D51="Electronics",H51*5%,IF(D51="Furniture",H51*8%,0)) -> 1970.4 | P51: =_xlfn.RANK.EQ(H51,$H$2:$H$201,0) -> 32 | Q51: =SUMIFS($H$2:$H$201,$B$2:$B$201,"<="&B51) -> 2761759
A52: 51 | B52: 45686 | C52: South | D52: Electronics | E52: Mobile | F52: Customer_40 | G52: Rahul | H52: 5943 | I52: 4384 | J52: =H52-I52 -> 1559 | K52: =J52/H52 -> 0.26232542 | L52: {=_xlfn.IFS(J52>15000,"Excellent",J52>=5000,"Good",J52<5000,"Poor")} -> Poor | M52: {=_xlfn.XLOOKUP(G52,' Employee_Salary'!$A$1:A56,' Employee_Salary'!$B$1:B56,FALSE)} -> 42000 | N52: =M52/H52 -> 7.0671378 | O52: =IF(D52="Electronics",H52*5%,IF(D52="Furniture",H52*8%,0)) -> 297.15 | P52: =_xlfn.RANK.EQ(H52,$H$2:$H$201,0) -> 177 | Q52: =SUMIFS($H$2:$H$201,$B$2:$B$201,"<="&B52) -> 1678740
A53: 52 | B53: 45700 | C53: West | D53: Furniture | E53: Cupboard | F53: Customer_32 | G53: Sneha | H53: 12216 | I53: 8895 | J53: =H53-I53 -> 3321 | K53: =J53/H53 -> 0.27185658 | L53: {=_xlfn.IFS(J53>15000,"Excellent",J53>=5000,"Good",J53<5000,"Poor")} -> Poor | M53: {=_xlfn.XLOOKUP(G53,' Employee_Salary'!$A$1:A57,' Employee_Salary'!$B$1:B57,FALSE)} -> 47000 | N53: =M53/H53 -> 3.8474132 | O53: =IF(D53="Electronics",H53*5%,IF(D53="Furniture",H53*8%,0)) -> 977.28 | P53: =_xlfn.RANK.EQ(H53,$H$2:$H$201,0) -> 140 | Q53: =SUMIFS($H$2:$H$201,$B$2:$B$201,"<="&B53) -> 2334388
A54: 53 | B54: 45669 | C54: North | D54: Furniture | E54: Cupboard | F54: Customer_1 | G54: Aisha | H54: 22306 | I54: 15746 | J54: =H54-I54 -> 6560 | K54: =J54/H54 -> 0.29409128 | L54: {=_xlfn.IFS(J54>15000,"Excellent",J54>=5000,"Good",J54<5000,"Poor")} -> Good | M54: {=_xlfn.XLOOKUP(G54,' Employee_Salary'!$A$1:A58,' Employee_Salary'!$B$1:B58,FALSE)} -> 45000 | N54: =M54/H54 -> 2.0173944 | O54: =IF(D54="Electronics",H54*5%,IF(D54="Furniture",H54*8%,0)) -> 1784.48 | P54: =_xlfn.RANK.EQ(H54,$H$2:$H$201,0) -> 51 | Q54: =SUMIFS($H$2:$H$201,$B$2:$B$201,"<="&B54) -> 665652
A55: 54 | B55: 45667 | C55: South | D55: Furniture | E55: Desk | F55: Customer_45 | G55: Farhan | H55: 17746 | I55: 11244 | J55: =H55-I55 -> 6502 | K55: =J55/H55 -> 0.36639243 | L55: {=_xlfn.IFS(J55>15000,"Excellent",J55>=5000,"Good",J55<5000,"Poor")} -> Good | M55: {=_xlfn.XLOOKUP(G55,' Employee_Salary'!$A$1:A59,' Employee_Salary'!$B$1:B59,FALSE)} -> 43000 | N55: =M55/H55 -> 2.4230813 | O55: =IF(D55="Electronics",H55*5%,IF(D55="Furniture",H55*8%,0)) -> 1419.68 | P55: =_xlfn.RANK.EQ(H55,$H$2:$H$201,0) -> 85 | Q55: =SUMIFS($H$2:$H$201,$B$2:$B$201,"<="&B55) -> 497964
A56: 55 | B56: 45717 | C56: West | D56: Electronics | E56: Tablet | F56: Customer_38 | G56: Aisha | H56: 17314 | I56: 12062 | J56: =H56-I56 -> 5252 | K56: =J56/H56 -> 0.30333834 | L56: {=_xlfn.IFS(J56>15000,"Excellent",J56>=5000,"Good",J56<5000,"Poor")} -> Good | M56: {=_xlfn.XLOOKUP(G56,' Employee_Salary'!$A$1:A60,' Employee_Salary'!$B$1:B60,FALSE)} -> 45000 | N56: =M56/H56 -> 2.5990528 | O56: =IF(D56="Electronics",H56*5%,IF(D56="Furniture",H56*8%,0)) -> 865.7 | P56: =_xlfn.RANK.EQ(H56,$H$2:$H$201,0) -> 91 | Q56: =SUMIFS($H$2:$H$201,$B$2:$B$201,"<="&B56) -> 3235200
A57: 56 | B57: 45678 | C57: South | D57: Furniture | E57: Table | F57: Customer_18 | G57: Rahul | H57: 26570 | I57: 20277 | J57: =H57-I57 -> 6293 | K57: =J57/H57 -> 0.23684607 | L57: {=_xlfn.IFS(J57>15000,"Excellent",J57>=5000,"Good",J57<5000,"Poor")} -> Good | M57: {=_xlfn.XLOOKUP(G57,' Employee_Salary'!$A$1:A61,' Employee_Salary'!$B$1:B61,FALSE)} -> 42000 | N57: =M57/H57 -> 1.5807301 | O57: =IF(D57="Electronics",H57*5%,IF(D57="Furniture",H57*8%,0)) -> 2125.6 | P57: =_xlfn.RANK.EQ(H57,$H$2:$H$201,0) -> 25 | Q57: =SUMIFS($H$2:$H$201,$B$2:$B$201,"<="&B57) -> 1191668
... A201: 200 | B201: 45683 | C201: East | D201: Electronics | E201: Headphones | F201: Customer_22 | G201: Nikhil | H201: 6437 | I201: 4292 | J201: =H201-I201 -> 2145 | K201: =J201/H201 -> 0.33322977 | L201: {=_xlfn.IFS(J201>15000,"Excellent",J201>=5000,"Good",J201<5000,"Poor")} -> Poor | M201: {=_xlfn.XLOOKUP(G201,' Employee_Salary'!$A$1:A205,' Employee_Salary'!$B$1:B205,FALSE)} -> 40000 | N201: =M201/H201 -> 6.2140749 | O201: =IF(D201="Electronics",H201*5%,IF(D201="Furniture",H201*8%,0)) -> 321.85 | P201: =_xlfn.RANK.EQ(H201,$H$2:$H$201,0) -> 174 | Q201: =SUMIFS($H$2:$H$201,$B$2:$B$201,"<="&B201) -> 1589196

Sheet Product
A1: {=_xlfn.UNIQUE(Assg!E1:E201)} -> Product | B1: Total revenue
A2: Table | B2: =SUMIF(Assg!E1:E201,Product!A2,Assg!H1:H201) -> 371146
A3: Desk | B3: =SUMIF(Assg!E2:E202,Product!A3,Assg!H2:H202) -> 492768
A4: Mobile | B4: =SUMIF(Assg!E3:E203,Product!A4,Assg!H3:H203) -> 381242
A5: Chair | B5: =SUMIF(Assg!E4:E204,Product!A5,Assg!H4:H204) -> 308621
A6: Laptop | B6: =SUMIF(Assg!E5:E205,Product!A6,Assg!H5:H205) -> 438222
A7: Headphones | B7: =SUMIF(Assg!E6:E206,Product!A7,Assg!H6:H206) -> 407463
A8: Tablet | B8: =SUMIF(Assg!E7:E207,Product!A8,Assg!H7:H207) -> 411456
A9: Cupboard | B9: =SUMIF(Assg!E8:E208,Product!A9,Assg!H8:H208) -> 424282

Sheet Pivot 1
A1: OrderID | B1: OrderDate | C1: Region | D1: Category | E1: Product | F1: CustomerName | G1: SalesPerson | H1: Sales | I1: Cost | J1: Profit | K1: Profit % | L1: Profit_performance | M1: Salary | N1: Sales_ratio | O1: Comission | P1: Rank | Q1: Running_total
A2: 1 | B2: 45660 | C2: West | D2: Furniture | E2: Table | F2: Customer_16 | G2: Sneha | H2: 5811 | I2: 5067 | J2: =H2-I2 -> 744 | K2: =J2/H2 -> 0.12803304 | L2: {=_xlfn.IFS(J2>15000,"Excellent",J2>=5000,"Good",J2<5000,"Poor")} -> Poor | M2: =_xlfn.XLOOKUP(G2,' Employee_Salary'!$A$2:$A$6,' Employee_Salary'!$B$2:$B$6) -> 47000 | N2: =M2/H2 -> 8.0881088 | O2: =IF(D2="Electronics",H2*5%,IF(D2="Furniture",H2*8%,0)) -> 464.88 | P2: =_xlfn.RANK.EQ(H2,$H$2:$H$201,0) -> 179 | Q2: =SUMIFS($H$2:$H$201,$B$2:$B$201,"<="&B2) -> 118866
A3: 2 | B3: 45710 | C3: North | D3: Furniture | E3: Desk | F3: Customer_19 | G3: Sneha | H3: 13553 | I3: 8173 | J3: =H3-I3 -> 5380 | K3: =J3/H3 -> 0.39696008 | L3: {=_xlfn.IFS(J3>15000,"Excellent",J3>=5000,"Good",J3<5000,"Poor")} -> Good | M3: =_xlfn.XLOOKUP(G3,' Employee_Salary'!$A$1:A7,' Employee_Salary'!$B$1:B7,FALSE) -> 47000 | N3: =M3/H3 -> 3.4678669 | O3: =IF(D3="Electronics",H3*5%,IF(D3="Furniture",H3*8%,0)) -> 1084.24 | P3: =_xlfn.RANK.EQ(H3,$H$2:$H$201,0) -> 120 | Q3: =SUMIFS($H$2:$H$201,$B$2:$B$201,"<="&B3) -> 2944836
A4: 3 | B4: 45714 | C4: South | D4: Electronics | E4: Mobile | F4: Customer_45 | G4: Sneha | H4: 7987 | I4: 5653 | J4: =H4-I4 -> 2334 | K4: =J4/H4 -> 0.29222487 | L4: {=_xlfn.IFS(J4>15000,"Excellent",J4>=5000,"Good",J4<5000,"Poor")} -> Poor | M4: {=_xlfn.XLOOKUP(G4,' Employee_Salary'!$A$1:A8,' Employee_Salary'!$B$1:B8,FALSE)} -> 47000 | N4: =M4/H4 -> 5.8845624 | O4: =IF(D4="Electronics",H4*5%,IF(D4="Furniture",H4*8%,0)) -> 399.35 | P4: =_xlfn.RANK.EQ(H4,$H$2:$H$201,0) -> 163 | Q4: =SUMIFS($H$2:$H$201,$B$2:$B$201,"<="&B4) -> 3096876
A5: 4 | B5: 45710 | C5: West | D5: Furniture | E5: Chair | F5: Customer_30 | G5: Farhan | H5: 3254 | I5: 2435 | J5: =H5-I5 -> 819 | K5: =J5/H5 -> 0.25169023 | L5: {=_xlfn.IFS(J5>15000,"Excellent",J5>=5000,"Good",J5<5000,"Poor")} -> Poor | M5: {=_xlfn.XLOOKUP(G5,' Employee_Salary'!$A$1:A9,' Employee_Salary'!$B$1:B9,FALSE)} -> 43000 | N5: =M5/H5 -> 13.214505 | O5: =IF(D5="Electronics",H5*5%,IF(D5="Furniture",H5*8%,0)) -> 260.32 | P5: =_xlfn.RANK.EQ(H5,$H$2:$H$201,0) -> 198 | Q5: =SUMIFS($H$2:$H$201,$B$2:$B$201,"<="&B5) -> 2944836
A6: 5 | B6: 45702 | C6: South | D6: Electronics | E6: Mobile | F6: Customer_40 | G6: Farhan | H6: 13732 | I6: 11076 | J6: =H6-I6 -> 2656 | K6: =J6/H6 -> 0.19341684 | L6: {=_xlfn.IFS(J6>15000,"Excellent",J6>=5000,"Good",J6<5000,"Poor")} -> Poor | M6: {=_xlfn.XLOOKUP(G6,' Employee_Salary'!$A$1:A10,' Employee_Salary'!$B$1:B10,FALSE)} -> 43000 | N6: =M6/H6 -> 3.131372 | O6: =IF(D6="Electronics",H6*5%,IF(D6="Furniture",H6*8%,0)) -> 686.6 | P6: =_xlfn.RANK.EQ(H6,$H$2:$H$201,0) -> 117 | Q6: =SUMIFS($H$2:$H$201,$B$2:$B$201,"<="&B6) -> 2448350
A7: 6 | B7: 45669 | C7: South | D7: Furniture | E7: Table | F7: Customer_34 | G7: Sneha | H7: 17328 | I7: 14130 | J7: =H7-I7 -> 3198 | K7: =J7/H7 -> 0.18455679 | L7: {=_xlfn.IFS(J7>15000,"Excellent",J7>=5000,"Good",J7<5000,"Poor")} -> Poor | M7: {=_xlfn.XLOOKUP(G7,' Employee_Salary'!$A$1:A11,' Employee_Salary'!$B$1:B11,FALSE)} -> 47000 | N7: =M7/H7 -> 2.712373 | O7: =IF(D7="Electronics",H7*5%,IF(D7="Furniture",H7*8%,0)) -> 1386.24 | P7: =_xlfn.RANK.EQ(H7,$H$2:$H$201,0) -> 90 | Q7: =SUMIFS($H$2:$H$201,$B$2:$B$201,"<="&B7) -> 665652
A8: 7 | B8: 45687 | C8: North | D8: Electronics | E8: Laptop | F8: Customer_14 | G8: Aisha | H8: 16650 | I8: 14634 | J8: =H8-I8 -> 2016 | K8: =J8/H8 -> 0.12108108 | L8: {=_xlfn.IFS(J8>15000,"Excellent",J8>=5000,"Good",J8<5000,"Poor")} -> Poor | M8: {=_xlfn.XLOOKUP(G8,' Employee_Salary'!$A$1:A12,' Employee_Salary'!$B$1:B12,FALSE)} -> 45000 | N8: =M8/H8 -> 2.7027027 | O8: =IF(D8="Electronics",H8*5%,IF(D8="Furniture",H8*8%,0)) -> 832.5 | P8: =_xlfn.RANK.EQ(H8,$H$2:$H$201,0) -> 101 | Q8: =SUMIFS($H$2:$H$201,$B$2:$B$201,"<="&B8) -> 1735136
A9: 8 | B9: 45661 | C9: South | D9: Electronics | E9: Headphones | F9: Customer_1 | G9: Sneha | H9: 4964 | I9: 3181 | J9: =H9-I9 -> 1783 | K9: =J9/H9 -> 0.35918614 | L9: {=_xlfn.IFS(J9>15000,"Excellent",J9>=5000,"Good",J9<5000,"Poor")} -> Poor | M9: {=_xlfn.XLOOKUP(G9,' Employee_Salary'!$A$1:A13,' Employee_Salary'!$B$1:B13,FALSE)} -> 47000 | N9: =M9/H9 -> 9.4681708 | O9: =IF(D9="Electronics",H9*5%,IF(D9="Furniture",H9*8%,0)) -> 248.2 | P9: =_xlfn.RANK.EQ(H9,$H$2:$H$201,0) -> 186 | Q9: =SUMIFS($H$2:$H$201,$B$2:$B$201,"<="&B9) -> 165400
A10: 9 | B10: 45705 | C10: North | D10: Furniture | E10: Table | F10: Customer_49 | G10: Farhan | H10: 19497 | I10: 16208 | J10: =H10-I10 -> 3289 | K10: =J10/H10 -> 0.16869262 | L10: {=_xlfn.IFS(J10>15000,"Excellent",J10>=5000,"Good",J10<5000,"Poor")} -> Poor | M10: {=_xlfn.XLOOKUP(G10,' Employee_Salary'!$A$1:A14,' Employee_Salary'!$B$1:B14,FALSE)} -> 43000 | N10: =M10/H10 -> 2.2054675 | O10: =IF(D10="Electronics",H10*5%,IF(D10="Furniture",H10*8%,0)) -> 1559.76 | P10: =_xlfn.RANK.EQ(H10,$H$2:$H$201,0) -> 70 | Q10: =SUMIFS($H$2:$H$201,$B$2:$B$201,"<="&B10) -> 2691046
A11: 10 | B11: 45693 | C11: South | D11: Electronics | E11: Tablet | F11: Customer_34 | G11: Rahul | H11: 29094 | I11: 19174 | J11: =H11-I11 -> 9920 | K11: =J11/H11 -> 0.34096377 | L11: {=_xlfn.IFS(J11>15000,"Excellent",J11>=5000,"Good",J11<5000,"Poor")} -> Good | M11: {=_xlfn.XLOOKUP(G11,' Employee_Salary'!$A$1:A15,' Employee_Salary'!$B$1:B15,FALSE)} -> 42000 | N11: =M11/H11 -> 1.4435966 | O11: =IF(D11="Electronics",H11*5%,IF(D11="Furniture",H11*8%,0)) -> 1454.7 | P11: =_xlfn.RANK.EQ(H11,$H$2:$H$201,0) -> 3 | Q11: =SUMIFS($H$2:$H$201,$B$2:$B$201,"<="&B11) -> 1945841
A12: 11 | B12: 45666 | C12: West | D12: Electronics | E12: Mobile | F12: Customer_39 | G12: Nikhil | H12: 27904 | I12: 24463 | J12: =H12-I12 -> 3441 | K12: =J12/H12 -> 0.12331565 | L12: {=_xlfn.IFS(J12>15000,"Excellent",J12>=5000,"Good",J12<5000,"Poor")} -> Poor | M12: {=_xlfn.XLOOKUP(G12,' Employee_Salary'!$A$1:A16,' Employee_Salary'!$B$1:B16,FALSE)} -> 40000 | N12: =M12/H12 -> 1.4334862 | O12: =IF(D12="Electronics",H12*5%,IF(D12="Furniture",H12*8%,0)) -> 1395.2 | P12: =_xlfn.RANK.EQ(H12,$H$2:$H$201,0) -> 14 | Q12: =SUMIFS($H$2:$H$201,$B$2:$B$201,"<="&B12) -> 480218
A13: 12 | B13: 45680 | C13: North | D13: Electronics | E13: Headphones | F13: Customer_23 | G13: Aisha | H13: 9233 | I13: 6766 | J13: =H13-I13 -> 2467 | K13: =J13/H13 -> 0.26719376 | L13: {=_xlfn.IFS(J13>15000,"Excellent",J13>=5000,"Good",J13<5000,"Poor")} -> Poor | M13: {=_xlfn.XLOOKUP(G13,' Employee_Salary'!$A$1:A17,' Employee_Salary'!$B$1:B17,FALSE)} -> 45000 | N13: =M13/H13 -> 4.8738222 | O13: =IF(D13="Electronics",H13*5%,IF(D13="Furniture",H13*8%,0)) -> 461.65 | P13: =_xlfn.RANK.EQ(H13,$H$2:$H$201,0) -> 155 | Q13: =SUMIFS($H$2:$H$201,$B$2:$B$201,"<="&B13) -> 1349916
A14: 13 | B14: 45713 | C14: East | D14: Furniture | E14: Desk | F14: Customer_38 | G14: Sneha | H14: 27329 | I14: 18038 | J14: =H14-I14 -> 9291 | K14: =J14/H14 -> 0.33996853 | L14: {=_xlfn.IFS(J14>15000,"Excellent",J14>=5000,"Good",J14<5000,"Poor")} -> Good | M14: {=_xlfn.XLOOKUP(G14,' Employee_Salary'!$A$1:A18,' Employee_Salary'!$B$1:B18,FALSE)} -> 47000 | N14: =M14/H14 -> 1.7197848 | O14: =IF(D14="Electronics",H14*5%,IF(D14="Furniture",H14*8%,0)) -> 2186.32 | P14: =_xlfn.RANK.EQ(H14,$H$2:$H$201,0) -> 19 | Q14: =SUMIFS($H$2:$H$201,$B$2:$B$201,"<="&B14) -> 3053221
A15: 14 | B15: 45700 | C15: West | D15: Furniture | E15: Desk | F15: Customer_5 | G15: Rahul | H15: 6994 | I15: 5062 | J15: =H15-I15 -> 1932 | K15: =J15/H15 -> 0.27623677 | L15: {=_xlfn.IFS(J15>15000,"Excellent",J15>=5000,"Good",J15<5000,"Poor")} -> Poor | M15: {=_xlfn.XLOOKUP(G15,' Employee_Salary'!$A$1:A19,' Employee_Salary'!$B$1:B19,FALSE)} -> 42000 | N15: =M15/H15 -> 6.0051473 | O15: =IF(D15="Electronics",H15*5%,IF(D15="Furniture",H15*8%,0)) -> 559.52 | P15: =_xlfn.RANK.EQ(H15,$H$2:$H$201,0) -> 171 | Q15: =SUMIFS($H$2:$H$201,$B$2:$B$201,"<="&B15) -> 2334388
... A201: 200 | B201: 45683 | C201: East | D201: Electronics | E201: Headphones | F201: Customer_22 | G201: Nikhil | H201: 6437 | I201: 4292 | J201: =H201-I201 -> 2145 | K201: =J201/H201 -> 0.33322977 | L201: {=_xlfn.IFS(J201>15000,"Excellent",J201>=5000,"Good",J201<5000,"Poor")} -> Poor | M201: {=_xlfn.XLOOKUP(G201,' Employee_Salary'!$A$1:A205,' Employee_Salary'!$B$1:B205,FALSE)} -> 40000 | N201: =M201/H201 -> 6.2140749 | O201: =IF(D201="Electronics",H201*5%,IF(D201="Furniture",H201*8%,0)) -> 321.85 | P201: =_xlfn.RANK.EQ(H201,$H$2:$H$201,0) -> 174 | Q201: =SUMIFS($H$2:$H$201,$B$2:$B$201,"<="&B201) -> 1589196

Sheet pivot Tables
H1: Salesman vs sales
A2: Region VS Total sales | H2: Row Labels | I2: Sum of Sales
A3: Row Labels | B3: Sum of Sales | F3: =H3 -> Aisha | H3: Aisha | I3: 750452
A4: East | B4: 788936 | H4: Farhan | I4: 693403
A5: North | B5: 698385 | H5: Nikhil | I5: 648534
A6: South | B6: 866015 | H6: Rahul | I6: 633574
A7: West | B7: 881864 | H7: Sneha | I7: 509237 | K7: % Grand Total
A8: Grand Total | B8: 3235200 | H8: Grand Total | I8: 3235200 | K8: Row Labels | L8: Sum of Sales
E9: Product Vs Profit | K9: East | L9: 0.24386004
E10: Row Labels | F10: Sum of Profit | K10: North | L10: 0.21587073
B11: =GETPIVOTDATA("Sales",$A$3) -> 3235200 | E11: Chair | F11: 75851 | K11: South | L11: 0.26768515
E12: Cupboard | F12: 96237 | K12: West | L12: 0.27258408
E13: Desk | F13: 116163 | H13: Monthly sales Summary | K13: Grand Total | L13: 1
E14: Headphones | F14: 95108 | H14: Row Labels | I14: Sum of Sales
A15: Section G – Pivot Tables | E15: Laptop | F15: 110535 | H15: Jan | I15: 1789203
A16: 24. Create Pivot ? Region vs Total Sales. | E16: Mobile | F16: 99690 | H16: Feb | I16: 1358687
A17: 25. Create Pivot ? Product vs Profit. | E17: Table | F17: 89706 | H17: Mar | I17: 87310
A18: 26. Create Pivot ? SalesPerson vs Sales. | E18: Tablet | F18: 104776 | H18: Grand Total | I18: 3235200
A19: 27. Create Monthly sales summary using Pivot. | E19: Grand Total | F19: 788066
A20: 28. Show % of Grand Total in Pivot.
F22: =GETPIVOTDATA("Profit",$E$10) -> 788066 | I22: {=E10:F19} -> Row Labels | J22: Sum of Profit
I23: Chair | J23: 75851
I24: Cupboard | J24: 96237
I25: Desk | J25: 116163
I26: Headphones | J26: 95108
A27: Row Labels | B27: Count of CustomerName | I27: Laptop | J27: 110535
A28: 1 | B28: 1 | I28: Mobile | J28: 99690
A29: 2 | B29: 1 | I29: Table | J29: 89706
A30: 3 | B30: 1 | I30: Tablet | J30: 104776 | K30: =MAX(J23:J30) -> 116163
A31: 4 | B31: 1 | I31: Grand Total | J31: 788066
A32: 5 | B32: 1
A33: 6 | B33: 1
A34: 7 | B34: 1
A35: 8 | B35: 1
A36: 9 | B36: 1
A37: 10 | B37: 1
A38: 11 | B38: 1
A39: 12 | B39: 1
A40: 13 | B40: 1
A41: 14 | B41: 1
A42: 15 | B42: 1
A43: 16 | B43: 1
... A227: 200 | B227: 1
A228: Grand Total | B228: 200
B231: =GETPIVOTDATA("CustomerName",$A$27) -> 200

Sheet Charts
A2: Column Chart Region vs Sales
A3: Row Labels | B3: Sum of Sales
A4: East | B4: 788936
A5: North | B5: 698385
A6: South | B6: 866015 | M6: Section H – Charts
A7: West | B7: 881864 | M7: 29. Column chart ? Region vs Sales.
A8: Grand Total | B8: 3235200 | M8: 30. Pie chart ? Category share.
M9: 31. Line chart ? Daily sales trend.
M10: 32. Bar chart ? SalesPerson ranking.
A20: Pie chart Categiry Share
A21: Row Labels | B21: Sum of Sales
A22: Electronics | B22: 1638383
A23: Furniture | B23: 1596817
A24: Grand Total | B24: 3235200
A37: Line chartDaily Sales Trend
A39: Row Labels | B39: Sum of Sales
A40: Jan | B40: 1789203
A41: Feb | B41: 1358687
A42: Mar | B42: 87310
A43: Grand Total | B43: 3235200
A55: Bar chart Sales person ranking
A56: Row Labels | B56: Sum of Sales
A57: Aisha | B57: 750452
A58: Farhan | B58: 693403
A59: Nikhil | B59: 648534
A60: Rahul | B60: 633574
A61: Sneha | B61: 509237
A62: Grand Total | B62: 3235200
B75: Section I – Dashboard (Main Project)
B76: 33. Create KPI cards:
B77: • Total Sales
B78: • Total Profit
B79: • Total Orders
B80: • Best SalesPerson
B81: 34. Add Slicers:
B82: • Region
B83: • Category
B84: • SalesPerson
B85: 35. Use GETPIVOTDATA to display KPI values.
B86: 36. Design one interactive dashboard sheet with all charts and KPIs.
B87: 37. Make the dashboard auto-update when data changes.

Sheet Dashboard

Sheet Final Task
B3: 1. West Region Has the Highest Sales
B5: The West region has the highest sales (881,864). The North region has the lowest sales (698385)
B7: Recommendation: Focus more on the North region by offering discounts or running marketing campaigns to increase sales.
B9: 2. Aisha is the Best SalesPerson
B11: Aisha has the highest sales (750452) among all salespeople. She is the best performer.
B13: Recommendation: Learn from Aisha's sales methods and help other salespeople improve their performance.
B15: 3. Furniture Sells Slightly More Than Electronics
B17: Furniture contributes 51% of total sales, while Electronics contributes 49%.
B19: Recommendation: Continue promoting Furniture and also run offers for Electronics to increase its sales.
B21: 4. The Business is Making Good Profit
B23: The company earned 3.24M in total sales and 788.1K in total profit from 200 orders.
B25: Recommendation: Increase the number of orders while maintaining good profit.
A27: 5. Sales Are Good in All Regions
B29: All four regions have good sales, but the West and South perform better than the North.
B31: Recommendation: Improve sales in the North region through better promotions and customer offers.
B33: 6. Desk product is the highest (116163) product got more sales
B35: Good thing that furniture has more sales
C37: Recommendation: provide some good discount to other electronics products also
